PyObjectInterface/WebController.py
PyObjectInterface/__init__.py
PyObjectInterface/web_controller.tpl.html
PyObjectInterface/examples/example.py
PyObjectInterface/examples/robot.py
pyobjectinterface-0.1.3.dist-info/licenses/LICENSE
pyobjectinterface-0.1.3.dist-info/METADATA
pyobjectinterface-0.1.3.dist-info/WHEEL
pyobjectinterface-0.1.3.dist-info/top_level.txt
pyobjectinterface-0.1.3.dist-info/RECORD
