Metadata-Version: 2.4
Name: PyObjectInterface
Version: 0.1.3
Summary: Create a web interface to interact with a class
Home-page: https://github.com/RobertJN64/PyObjectInterface
Author: Robert Nies
Author-email: robertjnies@gmail.com
License: MIT
Classifier: Programming Language :: Python
Classifier: Programming Language :: Python :: 3
Classifier: Programming Language :: Python :: 3 :: Only
Classifier: Programming Language :: Python :: 3.10
Classifier: Programming Language :: Python :: 3.11
Classifier: Programming Language :: Python :: 3.12
Classifier: Programming Language :: Python :: 3.13
Classifier: Programming Language :: Python :: 3.14
Requires-Python: >=3.10
License-File: LICENSE
Requires-Dist: typing_extensions
Requires-Dist: flask
Dynamic: license-file
